planned/__init__.py
planned/monitor.py
tests/__init__.py
tests/test_monitor.py
tests/test_process.py
planned-0.1.2.dist-info/LICENSE
planned-0.1.2.dist-info/METADATA
planned-0.1.2.dist-info/WHEEL
planned-0.1.2.dist-info/top_level.txt
planned-0.1.2.dist-info/RECORD
